wikia/__init__.py
wikia/exceptions.py
wikia/util.py
wikia/wikia.py
wikia-1.4.4.dist-info/LICENSE
wikia-1.4.4.dist-info/METADATA
wikia-1.4.4.dist-info/WHEEL
wikia-1.4.4.dist-info/top_level.txt
wikia-1.4.4.dist-info/RECORD
