Metadata-Version: 2.1
Name: wikia
Version: 1.4.4
Summary: Wikia API for Python
Home-page: https://github.com/Timidger/Wikia
Author: Preston Carpenter
Author-email: APragmaticPlace@gmail.com
License: MIT
Keywords: python wikipedia API
Platform: UNKNOWN
Classifier: License :: OSI Approved :: MIT License
Classifier: Programming Language :: Python
Classifier: Programming Language :: Python :: 3
Requires-Dist: beautifulsoup4
Requires-Dist: requests (<3.0.0,>=2.3.0)
